lazy_logging/__init__.py
bobs_lazy_logging-0.0.5.dist-info/METADATA
bobs_lazy_logging-0.0.5.dist-info/WHEEL
bobs_lazy_logging-0.0.5.dist-info/top_level.txt
bobs_lazy_logging-0.0.5.dist-info/RECORD
