Metadata-Version: 2.4
Name: bobs_lazy_logging
Version: 0.0.5
Summary: Debug logging for lazy people
Home-page: https://github.com/BobTheBuidler/lazy_logging
Author: BobTheBuidler
Author-email: bobthebuidlerdefi@gmail.com
License: MIT
Requires-Python: >=3.10,<4
Requires-Dist: typing_extensions>=4.4.0
Dynamic: author
Dynamic: author-email
Dynamic: home-page
Dynamic: license
Dynamic: requires-dist
Dynamic: requires-python
Dynamic: summary
